setup.cfg
setup.py
dutils/__init__.py
dutils/docstoc.py
dutils/gtranslator.py
dutils/gtranslator_constants.py
dutils/k.py
dutils/messaging.py
dutils/multiling.py
dutils/myapp.py
dutils/path.py
dutils/pld.py
dutils/pop3_mail.py
dutils/set_paths.py
dutils/shpaml.py
dutils/shpaml_loader.py
dutils/signals.py
dutils/spell_checker.py
dutils/test_shpaml.py
dutils/threadpool.py
dutils/urls.py
dutils/utils.py
dutils/wsgiserver.py
dutils.egg-info/PKG-INFO
dutils.egg-info/SOURCES.txt
dutils.egg-info/dependency_links.txt
dutils.egg-info/top_level.txt
dutils/kvds/__init__.py
dutils/kvds/common.py
dutils/kvds/exceptions.py
dutils/kvds/fields.py
dutils/kvds/models.py
dutils/kvds/sample.py
dutils/kvds/utils.py
dutils/kvds_server/__init__.py
dutils/kvds_server/forms.py
dutils/kvds_server/models.py
dutils/kvds_server/server.py
dutils/kvds_server/urls.py
dutils/kvds_server/utils.py
dutils/kvds_server/views.py
dutils/management/__init__.py
dutils/management/commands/__init__.py
dutils/management/commands/check_mail.py
dutils/management/commands/rdebug.py
dutils/management/commands/runwsgi.py
dutils/templatetags/__init__.py
dutils/templatetags/dutils_tags.py
dutils/templatetags/paginator.py