Metadata-Version: 1.0
Name: dutils
Version: 0.0.8
Summary: Useful django utilities
Home-page: http://github.com/amitu/dutils
Author: Amit Upadhyay
Author-email: code@amitu.com
License: UNKNOWN
Platform: UNKNOWN
